my_image_cropper/__init__.py
my_image_cropper/cropper.py
my_image_cropper-0.1.dist-info/METADATA
my_image_cropper-0.1.dist-info/WHEEL
my_image_cropper-0.1.dist-info/entry_points.txt
my_image_cropper-0.1.dist-info/top_level.txt
my_image_cropper-0.1.dist-info/RECORD
